contentalchemy/__init__.py
contentalchemy/content_formatters/__init__.py
contentalchemy/content_formatters/base.py
contentalchemy/images/__init__.py
contentalchemy/images/async_api/__init__.py
contentalchemy/images/async_api/snapper.py
contentalchemy/images/async_api/snapshot_template.html
contentalchemy/images/image_builders/__init__.py
contentalchemy/images/image_builders/datastructures.py
contentalchemy/images/sync_api/__init__.py
contentalchemy/images/sync_api/snapper.py
contentalchemy/images/sync_api/snapshot_template.html
contentalchemy-0.1.8.dist-info/METADATA
contentalchemy-0.1.8.dist-info/WHEEL
contentalchemy-0.1.8.dist-info/RECORD
